<!DOCTYPE frameset SYSTEM "frameset.dtd">
<frameset>
<predicate lemma="conversion">
<roleset id="conversion.01" name="transform" source="verb-convert.01" vncls="26.6">
<roles>

<role descr="causer of transformation" n="0">
<vnrole vncls="26.6" vntheta="Agent"/></role>

<role descr="thing changing" n="1">
<vnrole vncls="26.6" vntheta="Patient"/></role>

<role descr="end state" n="2">
<vnrole vncls="26.6" vntheta="Product"/></role>

<role descr="start state" n="3">
<vnrole vncls="26.6" vntheta="Material"/></role>

</roles>

<example name="autogen1">
<text>
the conversion of short-term claims inside the net to long-term
loans outside the net
</text>
<rel>conversion</rel>
<arg n="1">of short-term claims inside the net</arg>
<arg n="2">to long-term loans outside the net</arg>
</example>

<example name="autogen2">
<text>
Hearst had flirted with a conversion to tabloid format for years
but never executed the plan .
</text>
<arg n="0">Hearst</arg>
<arg n="Support">flirted with</arg>
<rel>conversion</rel>
<arg n="2">to tabloid format</arg>
</example>

</roleset>
</predicate>
</frameset>
