<!DOCTYPE frameset SYSTEM "frameset.dtd">
<frameset>
<predicate lemma="follower">
<roleset id="follower.01" name="adhere to, accept, pursue" source="verb-follow.02" vncls="51.6">
<roles>

<role descr="acceptor, pursuer" n="0">
<vnrole vncls="51.6" vntheta="Agent"/></role>

<role descr="thing followed" n="1">
<vnrole vncls="51.6" vntheta="Theme"/></role>

<role descr="beneficiary" n="2"></role>

</roles>

<example name="autogen1">
<text>
their followers
</text>
<arg n="1">their</arg>
<arg n="0">followers</arg>
<rel>followers</rel>
</example>

<example name="autogen2">
<text>
her husband 's followers
</text>
<arg n="1">her husband 's</arg>
<arg n="0">followers</arg>
<rel>followers</rel>
</example>

</roleset>
</predicate>
</frameset>
