<!DOCTYPE frameset SYSTEM "frameset.dtd">
<frameset>
<predicate lemma="secret">
<roleset id="secret.01" name="conceal" source="verb-hide.01" vncls="16">
<roles>

<role descr="hider" n="0">
<vnrole vncls="16" vntheta="Agent"/></role>

<role descr="thing hidden" n="1">
<vnrole vncls="16" vntheta="Patient"/></role>

<role descr="hidden from" n="2">
<vnrole vncls="16" vntheta="Recipient"/></role>

</roles>

<example name="autogen1">
<text>
a dozen competitors stealing your secrets at the same time
</text>
<arg n="2">a dozen competitors</arg>
<arg n="Support">stealing</arg>
<arg n="0">your</arg>
<arg f="REF" n="1">secrets</arg>
<rel>secrets</rel>
</example>

<example name="autogen2">
<text>
all Panama 's secrets
</text>
<arg n="0">all Panama 's</arg>
<arg f="REF" n="1">secrets</arg>
<rel>secrets</rel>
</example>

</roleset>
</predicate>
</frameset>
