<!DOCTYPE frameset SYSTEM "frameset.dtd">
<frameset>
<predicate lemma="vendetta">
<roleset id="vendetta.01" name="fight constantly" source="verb-feud.01" vncls="36.1">
<roles>

<role descr="first fighter" n="0">
<vnrole vncls="36.1" vntheta="Actor1"/></role>

<role descr="second fighter, if separate" n="1">
<vnrole vncls="36.1" vntheta="Actor2"/></role>

<role descr="spoils or point of contention" n="2">
<vnrole vncls="36.1" vntheta="Topic"/></role>

</roles>

<example name="autogen1">
<text>
a vendetta by state investigators and prosecutors angered by some
of his rulings against them
</text>
<rel>vendetta</rel>
<arg n="0">
by state investigators and prosecutors angered by some of his
rulings against them</arg>
</example>

<example name="autogen2">
<text>
a vendetta by a handful of disgruntled people
</text>
<rel>vendetta</rel>
<arg n="0">by a handful of disgruntled people</arg>
</example>

</roleset>
</predicate>
</frameset>
